tgmb/__init__.py
tgmb/__main__.py
tgmb-0.0.0b22.dist-info/LICENSE
tgmb-0.0.0b22.dist-info/METADATA
tgmb-0.0.0b22.dist-info/WHEEL
tgmb-0.0.0b22.dist-info/top_level.txt
tgmb-0.0.0b22.dist-info/RECORD
