Metadata-Version: 2.1
Name: tgmb
Version: 0.0.0b22
Summary: Predecessor to `tgmb`
Home-page: https://github.com/ksssomesh12/tgmb-beta
Author: SomesH S
Author-email: ksssomesh12@gmail.com
Project-URL: Bug Tracker, https://github.com/ksssomesh12/tgmb-beta/issues
Classifier: Programming Language :: Python :: 3
Classifier: License :: OSI Approved :: MIT License
Classifier: Operating System :: POSIX :: Linux
Classifier: Development Status :: 4 - Beta
Requires-Python: >=3.8
License-File: LICENSE
Requires-Dist: aria2p (==0.11.2)
Requires-Dist: google-api-python-client (==2.65.0)
Requires-Dist: google-auth-httplib2 (==0.1.0)
Requires-Dist: google-auth-oauthlib (==0.7.1)
Requires-Dist: psutil (==5.9.4)
Requires-Dist: python-magic (==0.4.27)
Requires-Dist: python-telegram-bot (==13.14)
Requires-Dist: qbittorrent-api (==2022.10.39)
Requires-Dist: torrentool (==1.1.1)
Requires-Dist: youtube-dl (==2021.12.17)
